sanitizer/__init__.py
sanitizer/cli.py
sanitizer/struct.py
paper_sanitizer-1.0.0.dist-info/METADATA
paper_sanitizer-1.0.0.dist-info/WHEEL
paper_sanitizer-1.0.0.dist-info/top_level.txt
paper_sanitizer-1.0.0.dist-info/RECORD
