Metadata-Version: 2.4
Name: paper-sanitizer
Version: 1.0.0
Summary: CLI that strips prompt-injection triggers from academic papers
Author-email: Thordur <thordur@gmail.com>
License: MIT
Classifier: Topic :: Security
Classifier: Topic :: Text Processing :: Markup :: LaTeX
Classifier: License :: OSI Approved :: MIT License
Classifier: Programming Language :: Python :: 3
Requires-Python: >=3.9
Requires-Dist: pdfminer.six>=20221105
Requires-Dist: pdfplumber>=0.11
Requires-Dist: pikepdf>=9.0
